cryptography_suite/__init__.py
cryptography_suite/aead.py
cryptography_suite/audit.py
cryptography_suite/cli.py
cryptography_suite/config.py
cryptography_suite/constants.py
cryptography_suite/debug.py
cryptography_suite/errors.py
cryptography_suite/exceptions.py
cryptography_suite/homomorphic.py
cryptography_suite/hybrid.py
cryptography_suite/nonce.py
cryptography_suite/pipeline.py
cryptography_suite/py.typed
cryptography_suite/rich_logging.py
cryptography_suite/utils.py
cryptography_suite/x509.py
cryptography_suite/asymmetric/__init__.py
cryptography_suite/asymmetric/bls.py
cryptography_suite/asymmetric/signatures.py
cryptography_suite/codegen/__init__.py
cryptography_suite/codegen/templates/README.md.j2
cryptography_suite/codegen/templates/fastapi/app.py.j2
cryptography_suite/codegen/templates/flask/app.py.j2
cryptography_suite/codegen/templates/node/app.ts.j2
cryptography_suite/crypto_backends/__init__.py
cryptography_suite/crypto_backends/abc.py
cryptography_suite/crypto_backends/pyca_backend.py
cryptography_suite/experimental/__init__.py
cryptography_suite/experimental/aes_gcm_sst.py
cryptography_suite/experimental/ascon.py
cryptography_suite/experimental/fhe.py
cryptography_suite/experimental/salsa20.py
cryptography_suite/experimental/zk.py
cryptography_suite/experimental/signal_demo/__init__.py
cryptography_suite/experimental/signal_demo/init_session.py
cryptography_suite/hashing/__init__.py
cryptography_suite/keystores/__init__.py
cryptography_suite/keystores/aws_kms.py
cryptography_suite/keystores/base.py
cryptography_suite/keystores/local.py
cryptography_suite/keystores/mock_hsm.py
cryptography_suite/keystores/pkcs11.py
cryptography_suite/legacy/__init__.py
cryptography_suite/optional/__init__.py
cryptography_suite/optional/salsa20.py
cryptography_suite/pqc/__init__.py
cryptography_suite/protocols/__init__.py
cryptography_suite/protocols/key_management.py
cryptography_suite/protocols/otp.py
cryptography_suite/protocols/pake.py
cryptography_suite-3.0.0.dist-info/licenses/LICENSE
cryptography_suite-3.0.0.dist-info/METADATA
cryptography_suite-3.0.0.dist-info/WHEEL
cryptography_suite-3.0.0.dist-info/entry_points.txt
cryptography_suite-3.0.0.dist-info/top_level.txt
cryptography_suite-3.0.0.dist-info/RECORD
