Metadata-Version: 2.4
Name: cryptography-suite
Version: 3.0.0
Summary: A comprehensive and secure cryptographic toolkit.
Author-email: Mojtaba Zaferanloo <psychevus@gmail.com>
License: MIT
Project-URL: Homepage, https://github.com/Psychevus/cryptography-suite
Project-URL: Documentation, https://psychevus.github.io/cryptography-suite
Project-URL: Source, https://github.com/Psychevus/cryptography-suite
Project-URL: Tracker, https://github.com/Psychevus/cryptography-suite/issues
Keywords: cryptography,encryption,security,AES,RSA,ChaCha20,Ed25519,ECDSA,hashing,PAKE,OTP,secret sharing
Classifier: Programming Language :: Python :: 3
Classifier: Programming Language :: Python :: 3.10
Classifier: Programming Language :: Python :: 3.11
Classifier: Programming Language :: Python :: 3.12
Classifier: License :: OSI Approved :: MIT License
Classifier: Operating System :: OS Independent
Classifier: Topic :: Security :: Cryptography
Classifier: Development Status :: 5 - Production/Stable
Classifier: Intended Audience :: Developers
Requires-Python: >=3.10
License-File: LICENSE
Requires-Dist: cryptography>=44.0.1
Requires-Dist: py_ecc
Requires-Dist: spake2
Requires-Dist: blake3
Requires-Dist: PyYAML
Requires-Dist: Jinja2
Requires-Dist: rich
Requires-Dist: ipywidgets
Requires-Dist: networkx
Requires-Dist: requests
Provides-Extra: pqc
Requires-Dist: pqcrypto; extra == "pqc"
Provides-Extra: fhe
Requires-Dist: Pyfhel; extra == "fhe"
Provides-Extra: zk
Requires-Dist: pybulletproofs; extra == "zk"
Requires-Dist: PySNARK; extra == "zk"
Provides-Extra: dev
Requires-Dist: pytest; extra == "dev"
Requires-Dist: pytest-cov; extra == "dev"
Requires-Dist: coverage; extra == "dev"
Requires-Dist: mypy; extra == "dev"
Requires-Dist: types-PyYAML; extra == "dev"
Requires-Dist: hypothesis; extra == "dev"
Requires-Dist: pytest-console-scripts; extra == "dev"
Provides-Extra: async
Requires-Dist: aiofiles; extra == "async"
Provides-Extra: docs
Requires-Dist: sphinx; extra == "docs"
Requires-Dist: furo; extra == "docs"
Requires-Dist: myst-parser; extra == "docs"
Requires-Dist: sphinxcontrib-mermaid; extra == "docs"
Provides-Extra: viz
Requires-Dist: rich; extra == "viz"
Requires-Dist: ipywidgets; extra == "viz"
Requires-Dist: networkx; extra == "viz"
Provides-Extra: aws
Requires-Dist: boto3; extra == "aws"
Provides-Extra: hsm
Requires-Dist: python-pkcs11>=0.8.1; extra == "hsm"
Provides-Extra: legacy
Requires-Dist: salsa20>=0.9; extra == "legacy"
Requires-Dist: ascon>=1.2; extra == "legacy"
Dynamic: license-file
